<?xml version="1.0" encoding="UTF-8"?><record_update table="question_choice">
    <question_choice action="INSERT_OR_UPDATE">
        <inactive>false</inactive>
        <order>5</order>
        <published_ref/>
        <question display_value="Nome do Material">2d8e11d29742b11044eb34100153af71</question>
        <sys_class_name>question_choice</sys_class_name>
        <sys_created_by>admin</sys_created_by>
        <sys_created_on>2023-10-25 01:01:25</sys_created_on>
        <sys_id>218e11d29742b11044eb34100153afc9</sys_id>
        <sys_mod_count>0</sys_mod_count>
        <sys_name>Lápis de Cor</sys_name>
        <sys_package display_value="Solicitação de Materiais Escolares" source="x_752986_solicit_0">013fdaf19706311044eb34100153afbc</sys_package>
        <sys_policy/>
        <sys_scope display_value="Solicitação de Materiais Escolares">013fdaf19706311044eb34100153afbc</sys_scope>
        <sys_update_name>question_choice_218e11d29742b11044eb34100153afc9</sys_update_name>
        <sys_updated_by>admin</sys_updated_by>
        <sys_updated_on>2023-10-25 01:01:25</sys_updated_on>
        <text>Lápis de Cor</text>
        <value>lapis_de_cor</value>
    </question_choice>
    <fx_price action="delete_multiple" query="id=218e11d29742b11044eb34100153afc9"/>
</record_update>
